Workbook

Sheet README
B2: Finished Goods Inventory & Demand Forecasting Optimization — FMCG Supply Chain
B3: Excel + SQL/Python demand forecasting model, ABC analysis, and reorder-point / safety-stock calculator — built for Mondelez-style finished goods (chocolates, biscuits, malted beverages, candy & gum, gifting).
B5: Sheet | C5: Contents
B6: Dashboard | C6: Executive KPI summary — fill-rate impact, forecast accuracy, ABC mix, and top reorder alerts, at a glance.
B7: SKU_Master | C7: Finished-goods SKU catalog: category, plant, distribution centers, cost, price, case pack, shelf life, lead time, MOQ (input data).
B8: Demand_Stats | C8: 90-day avg & std-dev daily demand per SKU, sourced from SQL (secondary sales / distributor off-take, v_sku_demand_stats_90d).
B9: ABC_Analysis | C9: Revenue-based Pareto classification (A/B/C) — LIVE Excel formulas (RANK, running SUM, IF).
B10: Reorder_Point_Calc | C10: Safety stock & reorder point per SKU — LIVE formulas, service level driven by ABC class; suggested order qty in cases.
B11: Fill_Rate_Impact | C11: Baseline vs simulated case-fill-rate after applying the new reorder policy, over a 12-week network simulation (before/after).
B12: Forecast_Model | C12: ML demand-forecast model comparison (WMAPE) and next-week forecast per SKU, incl. promo-calendar & festive-season features.
B13: Reorder_Alerts | C13: Automated, prioritized reorder alert list (urgency-ranked) — the AI-automation output.
B15: Color legend:
B16: Blue text = hardcoded input / external source (SQL extract, inventory snapshot, ML model output)
B17: Black text = live Excel formula
B19: Company context:
B20: Modeled on a Mondelez-style FMCG finished-goods network: 150 SKUs across 5 categories, 5 plants, 5 regional DCs (India).

Sheet Dashboard
B2: Mondelez — Finished Goods Inventory & Demand Forecasting Optimization
B3: FMCG Supply Chain — 150 SKUs | 5 Categories | 5 Plants | 5 Regional DCs
B5: TOTAL SKUs | D5: FILL RATE (AFTER) | F5: FORECAST ERROR (WMAPE)
B6: 150 | D6: =Fill_Rate_Impact!D6 -> 0.9874 | F6: =Forecast_Model!C7 -> 20.94
B8: Across 5 categories | D8: vs 74.6% before (+24.2 pp) | F8: vs 28.3% naive baseline
B9: REORDER ALERTS | D9: CRITICAL ALERTS | F9: WINNING MODEL
B10: 123 | D10: 43 | F10: Random Forest
B12: of 150 SKUs (82% of network) | D12: On-hand at/near stockout | F12: vs Naive / Moving Avg / Gradient Boosting
E29: Alerts by Urgency
E30: CRITICAL | F30: =COUNTIF(Reorder_Alerts!$I:$I,E30) -> 43
E31: HIGH | F31: =COUNTIF(Reorder_Alerts!$I:$I,E31) -> 26
E32: WATCH | F32: =COUNTIF(Reorder_Alerts!$I:$I,E32) -> 54

Sheet SKU_Master
A1: SKU ID | B1: SKU Name | C1: Category | D1: Unit Cost (₹) | E1: Unit Price (₹) | F1: Lead Time (days) | G1: MOQ (Cases) | H1: Case Pack (units/case) | I1: Shelf Life (days) | J1: Plant | K1: Distribution Centers (DCs)
A2: MDLZ0001 | B2: Cadbury 5 Star 24g | C2: Chocolates | D2: 48.25 | E2: 66.67 | F2: 2 | G2: 50 | H2: 36 | I2: 352 | J2: Malanpur (MP) | K2: DC-Central (Nagpur)|DC-East (Kolkata)|DC-South (Chennai)|DC-West (Mumbai)
A3: MDLZ0002 | B3: Dairy Milk Roast Almond 55g | C3: Chocolates | D3: 27.28 | E3: 41.68 | F3: 7 | G3: 25 | H3: 36 | I3: 345 | J3: Malanpur (MP) | K3: DC-East (Kolkata)|DC-North (Delhi-NCR)|DC-South (Chennai)
A4: MDLZ0003 | B4: Cadbury Dairy Milk 150g | C4: Chocolates | D4: 51.04 | E4: 73.47 | F4: 7 | G4: 20 | H4: 24 | I4: 342 | J4: Baddi (HP) | K4: DC-East (Kolkata)|DC-North (Delhi-NCR)|DC-South (Chennai)|DC-West (Mumbai)
A5: MDLZ0004 | B5: Cadbury Fuse 13g | C5: Chocolates | D5: 16.02 | E5: 23.31 | F5: 10 | G5: 20 | H5: 24 | I5: 358 | J5: Malanpur (MP) | K5: DC-East (Kolkata)|DC-North (Delhi-NCR)|DC-South (Chennai)|DC-West (Mumbai)
A6: MDLZ0005 | B6: Dairy Milk Silk 13g | C6: Chocolates | D6: 32.74 | E6: 43.15 | F6: 14 | G6: 25 | H6: 36 | I6: 334 | J6: Sri City (AP) | K6: DC-Central (Nagpur)|DC-East (Kolkata)|DC-North (Delhi-NCR)|DC-South (Chennai)
A7: MDLZ0006 | B7: Cadbury Perk 24g | C7: Chocolates | D7: 22.99 | E7: 33.44 | F7: 2 | G7: 100 | H7: 30 | I7: 331 | J7: Induri (Pune, MH) | K7: DC-Central (Nagpur)|DC-East (Kolkata)|DC-South (Chennai)|DC-West (Mumbai)
A8: MDLZ0007 | B8: Cadbury Bournville 80g | C8: Chocolates | D8: 31.86 | E8: 45.26 | F8: 3 | G8: 10 | H8: 24 | I8: 283 | J8: Malanpur (MP) | K8: DC-East (Kolkata)|DC-North (Delhi-NCR)|DC-South (Chennai)
A9: MDLZ0008 | B9: Cadbury 5 Star 80g | C9: Chocolates | D9: 36.79 | E9: 52.16 | F9: 4 | G9: 50 | H9: 42 | I9: 346 | J9: Induri (Pune, MH) | K9: DC-Central (Nagpur)|DC-North (Delhi-NCR)|DC-South (Chennai)|DC-West (Mumbai)
A10: MDLZ0009 | B10: Cadbury 5 Star 38g | C10: Chocolates | D10: 11.03 | E10: 14.72 | F10: 5 | G10: 50 | H10: 48 | I10: 298 | J10: Malanpur (MP) | K10: DC-Central (Nagpur)|DC-East (Kolkata)|DC-South (Chennai)|DC-West (Mumbai)
A11: MDLZ0010 | B11: Cadbury Crackle 80g | C11: Chocolates | D11: 9.18 | E11: 11.72 | F11: 10 | G11: 50 | H11: 24 | I11: 344 | J11: Induri (Pune, MH) | K11: DC-Central (Nagpur)|DC-North (Delhi-NCR)|DC-South (Chennai)|DC-West (Mumbai)
A12: MDLZ0011 | B12: Cadbury Crackle 24g | C12: Chocolates | D12: 27.81 | E12: 37.28 | F12: 7 | G12: 20 | H12: 42 | I12: 330 | J12: Induri (Pune, MH) | K12: DC-Central (Nagpur)|DC-West (Mumbai)
A13: MDLZ0012 | B13: Cadbury Bournville 110g | C13: Chocolates | D13: 44.38 | E13: 59.01 | F13: 14 | G13: 20 | H13: 48 | I13: 343 | J13: Sri City (AP) | K13: DC-Central (Nagpur)|DC-North (Delhi-NCR)|DC-South (Chennai)|DC-West (Mumbai)
... A151: MDLZ0150 | B151: Bournville Gift Pack 118g | C151: Premium Gifting | D151: 201.95 | E151: 248.75 | F151: 5 | G151: 100 | H151: 12 | I151: 312 | J151: Sri City (AP) | K151: DC-Central (Nagpur)|DC-East (Kolkata)|DC-South (Chennai)|DC-West (Mumbai)

Sheet Demand_Stats
A1: SKU ID | B1: Days Observed | C1: Avg Daily Demand | D1: Std Dev Daily Demand | F1: Source: SQL view v_sku_demand_stats_90d (02_demand_stats.sql), trailing 90 days of secondary-sales / distributor-offtake fact table.
A2: MDLZ0001 | B2: 90 | C2: 160.52 | D2: 89.01
A3: MDLZ0002 | B3: 90 | C3: 66.48 | D3: 43.63
A4: MDLZ0003 | B4: 90 | C4: 65.13 | D4: 35.96
A5: MDLZ0004 | B5: 90 | C5: 168.08 | D5: 70.85
A6: MDLZ0005 | B6: 90 | C6: 159.18 | D6: 70.14
A7: MDLZ0006 | B7: 90 | C7: 122.23 | D7: 53.02
A8: MDLZ0007 | B8: 90 | C8: 79.47 | D8: 36.25
A9: MDLZ0008 | B9: 90 | C9: 124.42 | D9: 57.58
A10: MDLZ0009 | B10: 90 | C10: 92.67 | D10: 37.99
A11: MDLZ0010 | B11: 90 | C11: 79.21 | D11: 49.72
A12: MDLZ0011 | B12: 90 | C12: 156.09 | D12: 77.98
A13: MDLZ0012 | B13: 90 | C13: 84.52 | D13: 35.32
... A151: MDLZ0150 | B151: 90 | C151: 35.49 | D151: 41.08

Sheet ABC_Analysis
A1: SKU ID | B1: Category | C1: Units Sold (12M) | D1: Revenue (12M, ₹) | E1: Revenue Rank | F1: Cumulative Revenue % | G1: ABC Class | I1: ABC Summary
A2: MDLZ0001 | B2: Chocolates | C2: 46018 | D2: 3068020.1 | E2: =RANK(D2,$D$2:$D$151) -> 31 | F2: =SUMPRODUCT(($E$2:$E$151<=E2)*$D$2:$D$151)/SUM($D$2:$D$151) -> 0.44160695 | G2: =IF(F2<=0.8,"A",IF(F2<=0.95,"B","C")) -> A | I2: Class | J2: SKU Count | K2: % of SKUs | L2: % of Revenue
A3: MDLZ0002 | B3: Chocolates | C3: 21522 | D3: 897036.96 | E3: =RANK(D3,$D$2:$D$151) -> 118 | F3: =SUMPRODUCT(($E$2:$E$151<=E3)*$D$2:$D$151)/SUM($D$2:$D$151) -> 0.93869434 | G3: =IF(F3<=0.8,"A",IF(F3<=0.95,"B","C")) -> B | I3: A | J3: =COUNTIF($G$2:$G$151,I3) -> 82 | K3: =J3/150 -> 0.54666667 | L3: =SUMIF($G$2:$G$151,I3,$D$2:$D$151)/SUM($D$2:$D$151) -> 0.79882464
A4: MDLZ0003 | B4: Chocolates | C4: 19731 | D4: 1449636.6 | E4: =RANK(D4,$D$2:$D$151) -> 87 | F4: =SUMPRODUCT(($E$2:$E$151<=E4)*$D$2:$D$151)/SUM($D$2:$D$151) -> 0.82305427 | G4: =IF(F4<=0.8,"A",IF(F4<=0.95,"B","C")) -> B | I4: B | J4: =COUNTIF($G$2:$G$151,I4) -> 40 | K4: =J4/150 -> 0.26666667 | L4: =SUMIF($G$2:$G$151,I4,$D$2:$D$151)/SUM($D$2:$D$151) -> 0.15105534
A5: MDLZ0004 | B5: Chocolates | C5: 55072 | D5: 1283728.3 | E5: =RANK(D5,$D$2:$D$151) -> 96 | F5: =SUMPRODUCT(($E$2:$E$151<=E5)*$D$2:$D$151)/SUM($D$2:$D$151) -> 0.86285334 | G5: =IF(F5<=0.8,"A",IF(F5<=0.95,"B","C")) -> B | I5: C | J5: =COUNTIF($G$2:$G$151,I5) -> 28 | K5: =J5/150 -> 0.18666667 | L5: =SUMIF($G$2:$G$151,I5,$D$2:$D$151)/SUM($D$2:$D$151) -> 0.050120016
A6: MDLZ0005 | B6: Chocolates | C6: 50424 | D6: 2175795.6 | E6: =RANK(D6,$D$2:$D$151) -> 53 | F6: =SUMPRODUCT(($E$2:$E$151<=E6)*$D$2:$D$151)/SUM($D$2:$D$151) -> 0.625256 | G6: =IF(F6<=0.8,"A",IF(F6<=0.95,"B","C")) -> A
A7: MDLZ0006 | B7: Chocolates | C7: 41109 | D7: 1374685 | E7: =RANK(D7,$D$2:$D$151) -> 91 | F7: =SUMPRODUCT(($E$2:$E$151<=E7)*$D$2:$D$151)/SUM($D$2:$D$151) -> 0.84114828 | G7: =IF(F7<=0.8,"A",IF(F7<=0.95,"B","C")) -> B
A8: MDLZ0007 | B8: Chocolates | C8: 30149 | D8: 1364543.7 | E8: =RANK(D8,$D$2:$D$151) -> 93 | F8: =SUMPRODUCT(($E$2:$E$151<=E8)*$D$2:$D$151)/SUM($D$2:$D$151) -> 0.85005301 | G8: =IF(F8<=0.8,"A",IF(F8<=0.95,"B","C")) -> B
A9: MDLZ0008 | B9: Chocolates | C9: 40043 | D9: 2088642.9 | E9: =RANK(D9,$D$2:$D$151) -> 57 | F9: =SUMPRODUCT(($E$2:$E$151<=E9)*$D$2:$D$151)/SUM($D$2:$D$151) -> 0.65288003 | G9: =IF(F9<=0.8,"A",IF(F9<=0.95,"B","C")) -> A
A10: MDLZ0009 | B10: Chocolates | C10: 32058 | D10: 471893.76 | E10: =RANK(D10,$D$2:$D$151) -> 137 | F10: =SUMPRODUCT(($E$2:$E$151<=E10)*$D$2:$D$151)/SUM($D$2:$D$151) -> 0.98289565 | G10: =IF(F10<=0.8,"A",IF(F10<=0.95,"B","C")) -> C
A11: MDLZ0010 | B11: Chocolates | C11: 21870 | D11: 256316.4 | E11: =RANK(D11,$D$2:$D$151) -> 150 | F11: =SUMPRODUCT(($E$2:$E$151<=E11)*$D$2:$D$151)/SUM($D$2:$D$151) -> 1 | G11: =IF(F11<=0.8,"A",IF(F11<=0.95,"B","C")) -> C
A12: MDLZ0011 | B12: Chocolates | C12: 48724 | D12: 1816430.7 | E12: =RANK(D12,$D$2:$D$151) -> 69 | F12: =SUMPRODUCT(($E$2:$E$151<=E12)*$D$2:$D$151)/SUM($D$2:$D$151) -> 0.72837901 | G12: =IF(F12<=0.8,"A",IF(F12<=0.95,"B","C")) -> A
A13: MDLZ0012 | B13: Chocolates | C13: 27550 | D13: 1625725.5 | E13: =RANK(D13,$D$2:$D$151) -> 77 | F13: =SUMPRODUCT(($E$2:$E$151<=E13)*$D$2:$D$151)/SUM($D$2:$D$151) -> 0.77334963 | G13: =IF(F13<=0.8,"A",IF(F13<=0.95,"B","C")) -> A
A14: MDLZ0013 | B14: Chocolates | C14: 101667 | D14: 4224263.8 | E14: =RANK(D14,$D$2:$D$151) -> 16 | F14: =SUMPRODUCT(($E$2:$E$151<=E14)*$D$2:$D$151)/SUM($D$2:$D$151) -> 0.27101869 | G14: =IF(F14<=0.8,"A",IF(F14<=0.95,"B","C")) -> A
A15: MDLZ0014 | B15: Chocolates | C15: 34319 | D15: 1902645.4 | E15: =RANK(D15,$D$2:$D$151) -> 65 | F15: =SUMPRODUCT(($E$2:$E$151<=E15)*$D$2:$D$151)/SUM($D$2:$D$151) -> 0.70426807 | G15: =IF(F15<=0.8,"A",IF(F15<=0.95,"B","C")) -> A
A16: MDLZ0015 | B16: Chocolates | C16: 19488 | D16: 387421.44 | E16: =RANK(D16,$D$2:$D$151) -> 148 | F16: =SUMPRODUCT(($E$2:$E$151<=E16)*$D$2:$D$151)/SUM($D$2:$D$151) -> 0.99791447 | G16: =IF(F16<=0.8,"A",IF(F16<=0.95,"B","C")) -> C
A17: MDLZ0016 | B17: Chocolates | C17: 27508 | D17: 2219345.4 | E17: =RANK(D17,$D$2:$D$151) -> 51 | F17: =SUMPRODUCT(($E$2:$E$151<=E17)*$D$2:$D$151)/SUM($D$2:$D$151) -> 0.61107266 | G17: =IF(F17<=0.8,"A",IF(F17<=0.95,"B","C")) -> A
... A151: MDLZ0150 | B151: Premium Gifting | C151: 9635 | D151: 2396706.2 | E151: =RANK(D151,$D$2:$D$151) -> 47 | F151: =SUMPRODUCT(($E$2:$E$151<=E151)*$D$2:$D$151)/SUM($D$2:$D$151) -> 0.58117696 | G151: =IF(F151<=0.8,"A",IF(F151<=0.95,"B","C")) -> A

Sheet Reorder_Point_Calc
A1: SKU ID | B1: ABC Class | C1: Avg Daily Demand | D1: Std Dev Demand | E1: Lead Time (days) | F1: Service Level Z | G1: Safety Stock (units) | H1: Reorder Point (units) | I1: Net On-Hand (units) | J1: Action | K1: Case Pack (units/case) | L1: Suggested Order Qty (units) | M1: Suggested Order Qty (Cases) | O1: Formulas: Safety Stock = Z x sigma(demand) x SQRT(Lead Time) | Reorder Point = (Avg Demand x Lead Time) + Safety Stock | Suggested Order Qty = MAX(0, Reorder Point + 10 days cycle stock - On-Hand)
A2: =SKU_Master!A2 -> MDLZ0001 | B2: =ABC_Analysis!G2 -> A | C2: =Demand_Stats!C2 -> 160.52 | D2: =Demand_Stats!D2 -> 89.01 | E2: =SKU_Master!F2 -> 2 | F2: =IF(B2="A",2.05,IF(B2="B",1.65,1.28)) -> 2.05 | G2: =ROUND(F2*D2*SQRT(E2),1) -> 258.1 | H2: =ROUND((C2*E2)+G2,1) -> 579.1 | I2: 113 | J2: =IF(I2<=H2,"REORDER NOW","OK") -> REORDER NOW | K2: =SKU_Master!H2 -> 36 | L2: =MAX(0,(H2+C2*10)-I2) -> 2071.3 | M2: =IF(K2=0,0,ROUNDUP(L2/K2,0)) -> 58
A3: =SKU_Master!A3 -> MDLZ0002 | B3: =ABC_Analysis!G3 -> B | C3: =Demand_Stats!C3 -> 66.48 | D3: =Demand_Stats!D3 -> 43.63 | E3: =SKU_Master!F3 -> 7 | F3: =IF(B3="A",2.05,IF(B3="B",1.65,1.28)) -> 1.65 | G3: =ROUND(F3*D3*SQRT(E3),1) -> 190.5 | H3: =ROUND((C3*E3)+G3,1) -> 655.9 | I3: 1140 | J3: =IF(I3<=H3,"REORDER NOW","OK") -> OK | K3: =SKU_Master!H3 -> 36 | L3: =MAX(0,(H3+C3*10)-I3) -> 180.7 | M3: =IF(K3=0,0,ROUNDUP(L3/K3,0)) -> 6
A4: =SKU_Master!A4 -> MDLZ0003 | B4: =ABC_Analysis!G4 -> B | C4: =Demand_Stats!C4 -> 65.13 | D4: =Demand_Stats!D4 -> 35.96 | E4: =SKU_Master!F4 -> 7 | F4: =IF(B4="A",2.05,IF(B4="B",1.65,1.28)) -> 1.65 | G4: =ROUND(F4*D4*SQRT(E4),1) -> 157 | H4: =ROUND((C4*E4)+G4,1) -> 612.9 | I4: 131 | J4: =IF(I4<=H4,"REORDER NOW","OK") -> REORDER NOW | K4: =SKU_Master!H4 -> 24 | L4: =MAX(0,(H4+C4*10)-I4) -> 1133.2 | M4: =IF(K4=0,0,ROUNDUP(L4/K4,0)) -> 48
A5: =SKU_Master!A5 -> MDLZ0004 | B5: =ABC_Analysis!G5 -> B | C5: =Demand_Stats!C5 -> 168.08 | D5: =Demand_Stats!D5 -> 70.85 | E5: =SKU_Master!F5 -> 10 | F5: =IF(B5="A",2.05,IF(B5="B",1.65,1.28)) -> 1.65 | G5: =ROUND(F5*D5*SQRT(E5),1) -> 369.7 | H5: =ROUND((C5*E5)+G5,1) -> 2050.5 | I5: 2401 | J5: =IF(I5<=H5,"REORDER NOW","OK") -> OK | K5: =SKU_Master!H5 -> 24 | L5: =MAX(0,(H5+C5*10)-I5) -> 1330.3 | M5: =IF(K5=0,0,ROUNDUP(L5/K5,0)) -> 56
A6: =SKU_Master!A6 -> MDLZ0005 | B6: =ABC_Analysis!G6 -> A | C6: =Demand_Stats!C6 -> 159.18 | D6: =Demand_Stats!D6 -> 70.14 | E6: =SKU_Master!F6 -> 14 | F6: =IF(B6="A",2.05,IF(B6="B",1.65,1.28)) -> 2.05 | G6: =ROUND(F6*D6*SQRT(E6),1) -> 538 | H6: =ROUND((C6*E6)+G6,1) -> 2766.5 | I6: 1142 | J6: =IF(I6<=H6,"REORDER NOW","OK") -> REORDER NOW | K6: =SKU_Master!H6 -> 36 | L6: =MAX(0,(H6+C6*10)-I6) -> 3216.3 | M6: =IF(K6=0,0,ROUNDUP(L6/K6,0)) -> 90
A7: =SKU_Master!A7 -> MDLZ0006 | B7: =ABC_Analysis!G7 -> B | C7: =Demand_Stats!C7 -> 122.23 | D7: =Demand_Stats!D7 -> 53.02 | E7: =SKU_Master!F7 -> 2 | F7: =IF(B7="A",2.05,IF(B7="B",1.65,1.28)) -> 1.65 | G7: =ROUND(F7*D7*SQRT(E7),1) -> 123.7 | H7: =ROUND((C7*E7)+G7,1) -> 368.2 | I7: 2 | J7: =IF(I7<=H7,"REORDER NOW","OK") -> REORDER NOW | K7: =SKU_Master!H7 -> 30 | L7: =MAX(0,(H7+C7*10)-I7) -> 1588.5 | M7: =IF(K7=0,0,ROUNDUP(L7/K7,0)) -> 53
A8: =SKU_Master!A8 -> MDLZ0007 | B8: =ABC_Analysis!G8 -> B | C8: =Demand_Stats!C8 -> 79.47 | D8: =Demand_Stats!D8 -> 36.25 | E8: =SKU_Master!F8 -> 3 | F8: =IF(B8="A",2.05,IF(B8="B",1.65,1.28)) -> 1.65 | G8: =ROUND(F8*D8*SQRT(E8),1) -> 103.6 | H8: =ROUND((C8*E8)+G8,1) -> 342 | I8: 55 | J8: =IF(I8<=H8,"REORDER NOW","OK") -> REORDER NOW | K8: =SKU_Master!H8 -> 24 | L8: =MAX(0,(H8+C8*10)-I8) -> 1081.7 | M8: =IF(K8=0,0,ROUNDUP(L8/K8,0)) -> 46
A9: =SKU_Master!A9 -> MDLZ0008 | B9: =ABC_Analysis!G9 -> A | C9: =Demand_Stats!C9 -> 124.42 | D9: =Demand_Stats!D9 -> 57.58 | E9: =SKU_Master!F9 -> 4 | F9: =IF(B9="A",2.05,IF(B9="B",1.65,1.28)) -> 2.05 | G9: =ROUND(F9*D9*SQRT(E9),1) -> 236.1 | H9: =ROUND((C9*E9)+G9,1) -> 733.8 | I9: 91 | J9: =IF(I9<=H9,"REORDER NOW","OK") -> REORDER NOW | K9: =SKU_Master!H9 -> 42 | L9: =MAX(0,(H9+C9*10)-I9) -> 1887 | M9: =IF(K9=0,0,ROUNDUP(L9/K9,0)) -> 45
A10: =SKU_Master!A10 -> MDLZ0009 | B10: =ABC_Analysis!G10 -> C | C10: =Demand_Stats!C10 -> 92.67 | D10: =Demand_Stats!D10 -> 37.99 | E10: =SKU_Master!F10 -> 5 | F10: =IF(B10="A",2.05,IF(B10="B",1.65,1.28)) -> 1.28 | G10: =ROUND(F10*D10*SQRT(E10),1) -> 108.7 | H10: =ROUND((C10*E10)+G10,1) -> 572.1 | I10: 90 | J10: =IF(I10<=H10,"REORDER NOW","OK") -> REORDER NOW | K10: =SKU_Master!H10 -> 48 | L10: =MAX(0,(H10+C10*10)-I10) -> 1408.8 | M10: =IF(K10=0,0,ROUNDUP(L10/K10,0)) -> 30
A11: =SKU_Master!A11 -> MDLZ0010 | B11: =ABC_Analysis!G11 -> C | C11: =Demand_Stats!C11 -> 79.21 | D11: =Demand_Stats!D11 -> 49.72 | E11: =SKU_Master!F11 -> 10 | F11: =IF(B11="A",2.05,IF(B11="B",1.65,1.28)) -> 1.28 | G11: =ROUND(F11*D11*SQRT(E11),1) -> 201.3 | H11: =ROUND((C11*E11)+G11,1) -> 993.4 | I11: 257 | J11: =IF(I11<=H11,"REORDER NOW","OK") -> REORDER NOW | K11: =SKU_Master!H11 -> 24 | L11: =MAX(0,(H11+C11*10)-I11) -> 1528.5 | M11: =IF(K11=0,0,ROUNDUP(L11/K11,0)) -> 64
A12: =SKU_Master!A12 -> MDLZ0011 | B12: =ABC_Analysis!G12 -> A | C12: =Demand_Stats!C12 -> 156.09 | D12: =Demand_Stats!D12 -> 77.98 | E12: =SKU_Master!F12 -> 7 | F12: =IF(B12="A",2.05,IF(B12="B",1.65,1.28)) -> 2.05 | G12: =ROUND(F12*D12*SQRT(E12),1) -> 422.9 | H12: =ROUND((C12*E12)+G12,1) -> 1515.5 | I12: 310 | J12: =IF(I12<=H12,"REORDER NOW","OK") -> REORDER NOW | K12: =SKU_Master!H12 -> 42 | L12: =MAX(0,(H12+C12*10)-I12) -> 2766.4 | M12: =IF(K12=0,0,ROUNDUP(L12/K12,0)) -> 66
A13: =SKU_Master!A13 -> MDLZ0012 | B13: =ABC_Analysis!G13 -> A | C13: =Demand_Stats!C13 -> 84.52 | D13: =Demand_Stats!D13 -> 35.32 | E13: =SKU_Master!F13 -> 14 | F13: =IF(B13="A",2.05,IF(B13="B",1.65,1.28)) -> 2.05 | G13: =ROUND(F13*D13*SQRT(E13),1) -> 270.9 | H13: =ROUND((C13*E13)+G13,1) -> 1454.2 | I13: 420 | J13: =IF(I13<=H13,"REORDER NOW","OK") -> REORDER NOW | K13: =SKU_Master!H13 -> 48 | L13: =MAX(0,(H13+C13*10)-I13) -> 1879.4 | M13: =IF(K13=0,0,ROUNDUP(L13/K13,0)) -> 40
... A151: =SKU_Master!A151 -> MDLZ0150 | B151: =ABC_Analysis!G151 -> A | C151: =Demand_Stats!C151 -> 35.49 | D151: =Demand_Stats!D151 -> 41.08 | E151: =SKU_Master!F151 -> 5 | F151: =IF(B151="A",2.05,IF(B151="B",1.65,1.28)) -> 2.05 | G151: =ROUND(F151*D151*SQRT(E151),1) -> 188.3 | H151: =ROUND((C151*E151)+G151,1) -> 365.8 | I151: 33 | J151: =IF(I151<=H151,"REORDER NOW","OK") -> REORDER NOW | K151: =SKU_Master!H151 -> 12 | L151: =MAX(0,(H151+C151*10)-I151) -> 687.7 | M151: =IF(K151=0,0,ROUNDUP(L151/K151,0)) -> 58

Sheet Fill_Rate_Impact
B2: Before vs After: Reorder Policy Impact (12-Week Network Simulation)
B3: AFTER = simulated result of replacing the naive weekly-review policy with the ABC-tiered, forecast-driven reorder-point policy from this workbook, across all 150 SKUs / 5 DCs, with a 30-day warm-up period before measurement (Gamma-Poisson demand, promo & festive-season spikes included).
B5: Fill Rate — BEFORE (naive weekly-review policy) | D5: 0.7459
B6: Fill Rate — AFTER (ABC-tiered, forecast-driven policy) | D6: 0.9874
B7: Improvement (percentage points) | D7: =D6-D5 -> 0.2415

Sheet Forecast_Model
B2: Demand Forecasting Model — Benchmark (WMAPE %, lower = better)
B4: Model | C4: WMAPE %
B5: Naive (last week) | C5: 28.31
B6: Moving Average (4wk) | C6: 25.76
B7: Random Forest | C7: 20.94
B8: Gradient Boosting | C8: 21.13
B10: Winning model: Random Forest (engineered lag + rolling-window + promo-calendar + festive-season features, weekly SKU-level demand).
B11: Trained/evaluated in Python (scikit-learn); see 03_forecasting_model.py. Time-based 8-week holdout, no leakage (all features causal; promo flags are the known-in-advance trade-promo calendar).
B30: Next-Week Demand Forecast (sample, top 15 by forecast volume)
B31: SKU ID | C31: Category | D31: Forecast Week | E31: Forecast Demand (units)
B32: MDLZ0013 | C32: Chocolates | D32: 2026-09-10 | E32: 2315.4
B33: MDLZ0120 | C33: Candy & Gum | D33: 2026-09-10 | E33: 1682.7
B34: MDLZ0092 | C34: Candy & Gum | D34: 2026-09-10 | E34: 1254.2
B35: MDLZ0004 | C35: Chocolates | D35: 2026-09-10 | E35: 1203.5
B36: MDLZ0100 | C36: Candy & Gum | D36: 2026-09-10 | E36: 1047.6
B37: MDLZ0102 | C37: Candy & Gum | D37: 2026-09-10 | E37: 1031.8
B38: MDLZ0011 | C38: Chocolates | D38: 2026-09-10 | E38: 1031.2
B39: MDLZ0005 | C39: Chocolates | D39: 2026-09-10 | E39: 1023.7
B40: MDLZ0001 | C40: Chocolates | D40: 2026-09-10 | E40: 1009.4
B41: MDLZ0023 | C41: Chocolates | D41: 2026-09-10 | E41: 997.2
B42: MDLZ0098 | C42: Candy & Gum | D42: 2026-09-10 | E42: 988.4
B43: MDLZ0091 | C43: Candy & Gum | D43: 2026-09-10 | E43: 965.3
... B46: MDLZ0116 | C46: Candy & Gum | D46: 2026-09-10 | E46: 886.5

Sheet Reorder_Alerts
B1: Automated Reorder Alerts (AI Automation Layer — prioritized, urgency-ranked)
A3: SKU ID | B3: SKU Name | C3: Category | D3: ABC Class | E3: On Hand | F3: Days of Cover | G3: Lead Time (days) | H3: Forecast Demand (next wk) | I3: Urgency | J3: Suggested Order Qty (units) | K3: Case Pack (units/case) | L3: Suggested Order Qty (Cases)
A4: MDLZ0006 | B4: Cadbury Perk 24g | C4: Chocolates | D4: B | E4: 2 | F4: 0 | G4: 2 | H4: 697.9 | I4: CRITICAL | J4: 1588 | K4: =INDEX(SKU_Master!$H:$H,MATCH(A4,SKU_Master!$A:$A,0)) -> 30 | L4: =IF(K4=0,0,ROUNDUP(J4/K4,0)) -> 53
A5: MDLZ0056 | B5: Oreo Chocolate Creme 120g | C5: Biscuits & Wafers | D5: B | E5: 2 | F5: 0 | G5: 7 | H5: 353.8 | I5: CRITICAL | J5: 1224 | K5: =INDEX(SKU_Master!$H:$H,MATCH(A5,SKU_Master!$A:$A,0)) -> 30 | L5: =IF(K5=0,0,ROUNDUP(J5/K5,0)) -> 41
A6: MDLZ0146 | B6: Toblerone Dark Chocolate 400g | C6: Premium Gifting | D6: B | E6: 1 | F6: 0.1 | G6: 3 | H6: 48.5 | I6: CRITICAL | J6: 243 | K6: =INDEX(SKU_Master!$H:$H,MATCH(A6,SKU_Master!$A:$A,0)) -> 6 | L6: =IF(K6=0,0,ROUNDUP(J6/K6,0)) -> 41
A7: MDLZ0125 | B7: Toblerone Dark Chocolate 59g | C7: Premium Gifting | D7: B | E7: 3 | F7: 0.2 | G7: 5 | H7: 49.5 | I7: CRITICAL | J7: 283 | K7: =INDEX(SKU_Master!$H:$H,MATCH(A7,SKU_Master!$A:$A,0)) -> 12 | L7: =IF(K7=0,0,ROUNDUP(J7/K7,0)) -> 24
A8: MDLZ0082 | B8: Bournvita Duo Chocolate 2kg | C8: Malted Beverages | D8: B | E8: 5 | F8: 0.3 | G8: 4 | H8: 114.9 | I8: CRITICAL | J8: 264 | K8: =INDEX(SKU_Master!$H:$H,MATCH(A8,SKU_Master!$A:$A,0)) -> 18 | L8: =IF(K8=0,0,ROUNDUP(J8/K8,0)) -> 15
A9: MDLZ0099 | B9: Halls Strawberry Stickpack 10pc | C9: Candy & Gum | D9: B | E9: 29 | F9: 0.3 | G9: 4 | H9: 693.5 | I9: CRITICAL | J9: 1656 | K9: =INDEX(SKU_Master!$H:$H,MATCH(A9,SKU_Master!$A:$A,0)) -> 24 | L9: =IF(K9=0,0,ROUNDUP(J9/K9,0)) -> 69
A10: MDLZ0148 | B10: Toblerone White Chocolate 118g | C10: Premium Gifting | D10: B | E10: 4 | F10: 0.3 | G10: 3 | H10: 43.3 | I10: CRITICAL | J10: 204 | K10: =INDEX(SKU_Master!$H:$H,MATCH(A10,SKU_Master!$A:$A,0)) -> 12 | L10: =IF(K10=0,0,ROUNDUP(J10/K10,0)) -> 17
A11: MDLZ0025 | B11: Dairy Milk Silk Bubbly 110g | C11: Chocolates | D11: B | E11: 17 | F11: 0.4 | G11: 5 | H11: 360.7 | I11: CRITICAL | J11: 766 | K11: =INDEX(SKU_Master!$H:$H,MATCH(A11,SKU_Master!$A:$A,0)) -> 36 | L11: =IF(K11=0,0,ROUNDUP(J11/K11,0)) -> 22
A12: MDLZ0072 | B12: Bournvita 5Star Magic Jar 2kg | C12: Malted Beverages | D12: B | E12: 5 | F12: 0.4 | G12: 10 | H12: 76.4 | I12: CRITICAL | J12: 264 | K12: =INDEX(SKU_Master!$H:$H,MATCH(A12,SKU_Master!$A:$A,0)) -> 24 | L12: =IF(K12=0,0,ROUNDUP(J12/K12,0)) -> 11
A13: MDLZ0109 | B13: Halls Orange Pouch 100pc | C13: Candy & Gum | D13: B | E13: 47 | F13: 0.4 | G13: 5 | H13: 773.3 | I13: CRITICAL | J13: 1754 | K13: =INDEX(SKU_Master!$H:$H,MATCH(A13,SKU_Master!$A:$A,0)) -> 36 | L13: =IF(K13=0,0,ROUNDUP(J13/K13,0)) -> 49
A14: MDLZ0120 | B14: Chiclets Spearmint Stickpack 10pc | C14: Candy & Gum | D14: A | E14: 98 | F14: 0.4 | G14: 5 | H14: 1682.7 | I14: CRITICAL | J14: 3848 | K14: =INDEX(SKU_Master!$H:$H,MATCH(A14,SKU_Master!$A:$A,0)) -> 60 | L14: =IF(K14=0,0,ROUNDUP(J14/K14,0)) -> 65
A15: MDLZ0029 | B15: Cadbury Bournville 24g | C15: Chocolates | D15: B | E15: 48 | F15: 0.5 | G15: 3 | H15: 690.3 | I15: CRITICAL | J15: 1341 | K15: =INDEX(SKU_Master!$H:$H,MATCH(A15,SKU_Master!$A:$A,0)) -> 48 | L15: =IF(K15=0,0,ROUNDUP(J15/K15,0)) -> 28
... A126: MDLZ0097 | B126: Chiclets Spearmint Jar 300g | C126: Candy & Gum | D126: B | E126: 1159 | F126: 13.2 | G126: 14 | H126: 656.4 | I126: WATCH | J126: 1187 | K126: =INDEX(SKU_Master!$H:$H,MATCH(A126,SKU_Master!$A:$A,0)) -> 36 | L126: =IF(K126=0,0,ROUNDUP(J126/K126,0)) -> 33
A128: 123 of 150 SKUs flagged for reorder (82.0% of the network) — ranked CRITICAL > HIGH > WATCH, then by days of cover ascending.
